sn2md/__init__.py
sn2md/__main__.py
sn2md/ai_utils.py
sn2md/cli.py
sn2md/importer.py
sn2md/metadata.py
sn2md/types.py
sn2md/importers/atelier.py
sn2md/importers/note.py
sn2md/importers/pdf.py
sn2md/importers/png.py
sn2md-2.6.0.dist-info/licenses/LICENSE
sn2md-2.6.0.dist-info/METADATA
sn2md-2.6.0.dist-info/WHEEL
sn2md-2.6.0.dist-info/entry_points.txt
sn2md-2.6.0.dist-info/top_level.txt
sn2md-2.6.0.dist-info/RECORD
