Metadata-Version: 2.4
Name: sn2md
Version: 2.6.0
Summary: Convert Supernote .note, .spd, PDF, or image files to text/images
Author-email: Dane Summers <dsummersl@gmail.com>
Project-URL: homepage, https://github.com/dsummersl/sn2md
Project-URL: issues, https://github.com/dsummersl/sn2md/issues
Classifier: Programming Language :: Python :: 3
Classifier: Typing :: Typed
Requires-Python: >=3.11
License-File: LICENSE
Requires-Dist: click<9.0,>=8.1.7
Requires-Dist: supernotelib<1.0,>=0.6.2
Requires-Dist: pyyaml<7.0,>=6.0.1
Requires-Dist: platformdirs<5.0,>=4.2.2
Requires-Dist: jinja2<4.0,>=3.1.4
Requires-Dist: llm<1.0,>=0.26
Requires-Dist: pymupdf<2.0,>=1.25.2
Requires-Dist: tqdm<5.0,>=4.67.1
Requires-Dist: pydantic<3.0,>=2.10.6
Dynamic: license-file
